{"type": "Feature", "id": 12514165, "geometry": {"type": "Point", "coordinates": [125.906898, 39.244499]}, "properties": {"woe:id": 12514165, "woe:parent_id": 1093926, "woe:name": "Pyong Ni South Highway Strip Airport", "woe:placetype": 14, "woe:placetype_name": "Airport", "woe:lang": "ENG", "iso:country": "KP", "meta:provider": ["geoplanet:7.3.1", "geoplanet:7.3.2", "geoplanet:7.4.0", "geoplanet:7.4.1", "geoplanet:7.5.1", "geoplanet:7.5.2", "geoplanet:7.6.0", "geoplanet:7.8.1", "geoplanet:7.9.0", "geoplanet:7.10.0", "geoplanet:8.0.0", "woeplanet:8.0.0"], "meta:indexed": "2020-08-20T20:19:21.311646", "meta:updated": "2020-10-14T11:16:42.655573", "woe:hierarchy": {"continent": 24865671, "country": 23424865, "town": 0, "planet": 1, "county": 0, "suburb": 0, "state": 2345957, "region": 0, "localadmin": 0}, "woe:timezone_id": 28350848, "woe:hash": "wycx304xg2ge", "woe:centroid": [125.906898, 39.244499], "geom:latitude": 39.244499, "geom:longitude": 125.906898, "geom:hash": "wycx304xg2ge", "woe:latitude": 39.244499, "geom:centroid": [125.906898, 39.244499], "woe:longitude": 125.906898, "woe:repo": "woeplanet-airport-kp", "geom:area": 0.0, "woe:scale": 19}}