{"type": "Feature", "id": 12514143, "geometry": {"type": "Point", "coordinates": [126.066704, 39.095402]}, "properties": {"woe:id": 12514143, "woe:parent_id": 1093890, "woe:name": "Kangdong Airport", "woe:placetype": 14, "woe:placetype_name": "Airport", "woe:lang": "ENG", "iso:country": "KP", "meta:provider": ["geoplanet:7.3.1", "geoplanet:7.3.2", "geoplanet:7.4.0", "geoplanet:7.4.1", "geoplanet:7.5.1", "geoplanet:7.5.2", "geoplanet:7.6.0", "geoplanet:7.8.1", "geoplanet:7.9.0", "geoplanet:7.10.0", "geoplanet:8.0.0", "woeplanet:8.0.0"], "meta:indexed": "2020-08-20T20:19:21.291726", "meta:updated": "2020-10-14T11:16:42.667315", "woe:hierarchy": {"continent": 24865671, "country": 23424865, "town": 0, "planet": 1, "county": 0, "suburb": 0, "state": 2345957, "region": 0, "localadmin": 0}, "woe:timezone_id": 28350848, "woe:hash": "wycwktngpp5s", "woe:centroid": [126.066704, 39.095402], "geom:latitude": 39.095402, "geom:longitude": 126.066704, "geom:hash": "wycwktngpp5s", "woe:latitude": 39.095402, "geom:centroid": [126.066704, 39.095402], "woe:longitude": 126.066704, "woe:repo": "woeplanet-airport-kp", "geom:area": 0.0, "woe:scale": 19}}